xsocks5/__init__.py
xsocks5/main.py
xsocks5-0.1.2.dist-info/METADATA
xsocks5-0.1.2.dist-info/WHEEL
xsocks5-0.1.2.dist-info/entry_points.txt
xsocks5-0.1.2.dist-info/RECORD
