Metadata-Version: 2.4
Name: xsocks5
Version: 0.1.2
Summary: A SOCKS5 proxy
Project-URL: Homepage, https://github.com/Simple-Creator/socks5-python
Project-URL: Repository, https://github.com/Simple-Creator/socks5-python
Project-URL: Issues, https://github.com/Simple-Creator/socks5-python/issues
Author-email: SimpleCreator <ipowerink@gmail.com>
License: MIT
Requires-Python: >=3.11
Requires-Dist: asyncio>=4.0.0
